Metadata-Version: 1.0
Name: distributions-arief
Version: 0.2
Summary: Gaussian distributions
Home-page: UNKNOWN
Author: Arief Ramadhan
Author-email: arief25ramadhan@gmail.com
License: UNKNOWN
Platform: UNKNOWN
